{
  "sortedOrder": 0,
  "hasHabitableWorld": 0,
  "discoveryFacility": "Microlensing",
  "particlesFun": false,
  "type": "Exoplanets",
  "pl_pnum": 1,
  "publishDate": 1654205887014,
  "hasPublishDate": true,
  "g": 39.5,
  "dt": 0.000005,
  "distMax": 50,
  "distMin": -50,
  "rotatingReferenceFrame": "OGLE-2018-BLG-0383L",
  "cameraPosition": "Free",
  "particles": { "max": 20000, "size": 10, "rings": [] },
  "massBeingModified": "Mars",
  "primary": "OGLE-2018-BLG-0383L",
  "maximumDistance": { "name": "Phobos to Mars * 100", "value": 0.00626747 },
  "distanceStep": { "name": "Phobos to Mars / 10", "value": 0.00000626747 },
  "systemBarycenter": true,
  "barycenter": false,
  "barycenterMassOne": "OGLE-2018-BLG-0383L",
  "barycenterMassTwo": "OGLE-2018-BLG-0383L",
  "tol": 0.0001,
  "maxDt": 0.001,
  "minDt": 0.000001,
  "isLoaded": false,
  "playing": false,
  "integrator": "PEFRL",
  "customCameraToBodyDistanceFactor": false,
  "barycenterZ": 11340000,
  "elapsedTime": 0,
  "useBarnesHut": false,
  "theta": 0.5,
  "collisions": false,
  "habitableZone": false,
  "mapMode": true,
  "referenceOrbits": false,
  "softeningConstant": 0,
  "logarithmicDepthBuffer": true,
  "scale": 2100000,
  "trails": false,
  "labels": true,
  "velMax": 5,
  "velMin": -5,
  "velStep": 0.00000185765499287888,
  "isMassBeingAdded": false,
  "a": 0,
  "e": 0,
  "w": 0,
  "i": 0,
  "o": 0,
  "masses": [
    {
      "name": "OGLE-2018-BLG-0383L",
      "m": 0.1,
      "radius": 1164.2790697674418,
      "temperature": null,
      "massType": "star"
    },
    {
      "name": "OGLE-2018-BLG-0383L-b",
      "texture": "OGLE-2018-BLG-0383L-b",
      "m": 0.000019219602000000004,
      "worldType": "ice giant",
      "atmosphere": "dodgerblue",
      "discoveryFacility": "Microlensing",
      "potentiallyHabitableWorld": false,
      "radius": 210,
      "a": 1.8,
      "e": null,
      "w": 216.80993146227377,
      "i": 0,
      "o": 0,
      "orbitalPeriod": null,
      "temperature": 31.88696399116154,
      "exoplanet": true,
      "bump": false,
      "color": "#2785FB",
      "clouds": false,
      "customCameraPosition": { "x": 2, "y": 2, "z": 0 }
    }
  ],
  "hallOfFame": false,
  "scenarioDescription": "\n  <ul class=\"exoplanets-navigation-menu\">\n  <li><button href=\"#system\">System</button>\n  <li><button href=\"#OGLE-2018-BLG-0383L\">Star</button>\n  <li><button href=\"#OGLE-2018-BLG-0383L-b\">b</button></li>\n  </ul>\n  <h1 id=\"system\">The OGLE-2018-BLG-0383L Exoplanetary System</h1>\n  <p>The OGLE-2018-BLG-0383L system contains 1 exoplanet. It is located 25114.01 light years away from the solar system.</p>\n    <div class=\"celestial-object-wrapper\" id=\"OGLE-2018-BLG-0383L\">\n  <section>\n  <h2>Star</h2>\n  <div class=\"size-comparison-wrapper\">\n  <div class=\"celestial-sphere\" style=\"width: 100px; height: 100px; background-color: rgb(255, 242.3979365143785, 230.54885609599933);\">\n    <label>Sun</label>\n  </div>\n  <div class=\"celestial-sphere\" style=\"width: 11.92px; height: 11.92px; background-color: rgb(NaN, NaN, 255)\">\n<label>OGLE-2018-BLG-0383L</label>\n</div>\n</div>\n  </section>\n  <table cellspacing=\"0\">\n  <tr>\n    <td>Mass</td>\n    <td>0.1 solar masses</td>\n  </tr>\n  <tr>\n    <td>Radius</td>\n    <td>0.1192 solar radiae</td>\n  </tr>\n  <tr>\n    <td>Temperature</td>\n    <td>- kelvin</td>\n  </tr>\n  <tr>\n    <td>Stellar Metallicity</td>\n    <td>- decimal exponent</td>\n  </tr>\n  <tr>\n    <td>Age</td>\n    <td>- billion years</td>\n  </tr>\n</table>\n</div>\n     \n    <div class=\"celestial-object-wrapper\" id=\"OGLE-2018-BLG-0383L-b\">\n      <section>\n        <h2>OGLE-2018-BLG-0383L-b</h2>\n        <p>    At more than 10 Earth masses, OGLE-2018-BLG-0383L b is an ice giant, a planet that is made up mostly of volatiles like water, amonia and methane, and enveloped by a dense hydrogen and helium atmosphere, much like Uranus and Neptune.  </p>\n        <div class=\"size-comparison-wrapper\">\n          <div class=\"celestial-sphere\" style=\"width: 10px; height: 10px;\">\n            <label>Earth</label>\n          </div>\n          <div class=\"celestial-sphere\" style=\"width: 24.1px; height: 24.1px;\">\n            <label>OGLE-2018-BLG-0383L-b</label>\n          </div>\n        </div>\n        <table cellspacing=\"0\">\n          <tr>\n            <td>Mass</td>\n            <td>6.400 Earth masses</td>\n          </tr>\n          <tr>\n            <td>Density</td>\n            <td>2.510 grams per cubic centimeter</td>\n          </tr>\n          <tr>\n            <td>Radius</td>\n            <td>2.410 Earth radiae</td>\n          </tr>\n          <tr>\n            <td>Semi-major Axis</td>\n            <td>1.8 AU</td>\n          </tr>\n          <tr>\n            <td>Eccentricity</td>\n            <td>NaN</td>\n          </tr>\n          <tr>\n            <td>Orbital Period</td>\n            <td>NaN days</td>\n          </tr>\n          <tr>\n            <td>Discovery Method</td>\n            <td>Microlensing</td>\n          </tr>\n          <tr>\n            <td>Discovery Facility</td>\n            <td>OGLE</td>\n          </tr>\n          <tr>\n            <td>Discovery Telescope</td>\n            <td>1.3 m Warsaw University Telescope</td>\n          </tr>\n          <tr>\n            <td>Discovery Instrument</td>\n            <td>OGLE CCD Array</td>\n          </tr>\n          <tr>\n            <td>Discovery Date</td>\n            <td>2022-02</td>\n          </tr>\n          <tr>\n            <td>Reference</td>\n            <td><a refstr=WANG_ET_AL__2022 href=https://ui.adsabs.harvard.edu/abs/2022MNRAS.510.1778W/abstract target=ref>Wang et al. 2022</a></td>\n          </tr>\n        </table>\n      </section>\n    </div></a>\n  ",
  "description": "3D visualisation and gravity simulation of the exoplanetary system OGLE-2018-BLG-0383L, which contains 1 exoplanets and was discovered by the OGLE.",
  "name": "OGLE-2018-BLG-0383L - System With 1 Exoplanet ",
  "cameraFocus": "Barycenter",
  "fileName": "OGLE-2018-BLG-0383L - System With 1 Exoplanet "
}
