{"sortedOrder":0,"hasHabitableWorld":0,"discoveryFacility":"Transit","particlesFun":false,"type":"Exoplanets","pl_pnum":1,"publishDate":1660075941130,"hasPublishDate":true,"g":39.5,"dt":0.000005,"distMax":50,"distMin":-50,"rotatingReferenceFrame":"TOI-3629","cameraPosition":"Free","particles":{"max":20000,"size":10,"rings":[]},"massBeingModified":"Mars","primary":"TOI-3629","maximumDistance":{"name":"Phobos to Mars * 100","value":0.00626747},"distanceStep":{"name":"Phobos to Mars / 10","value":0.00000626747},"systemBarycenter":true,"barycenter":false,"barycenterMassOne":"TOI-3629","barycenterMassTwo":"TOI-3629","tol":0.0001,"maxDt":0.001,"minDt":0.000001,"isLoaded":false,"playing":false,"integrator":"PEFRL","customCameraToBodyDistanceFactor":false,"barycenterZ":270900,"elapsedTime":0,"useBarnesHut":false,"theta":0.5,"collisions":false,"habitableZone":false,"mapMode":true,"referenceOrbits":false,"softeningConstant":0,"logarithmicDepthBuffer":true,"scale":2100000,"trails":false,"labels":true,"velMax":5,"velMin":-5,"velStep":0.00000185765499287888,"isMassBeingAdded":false,"a":0,"e":0,"w":0,"i":0,"o":0,"masses":[{"name":"TOI-3629","m":0.63,"radius":5860.46511627907,"temperature":3870,"massType":"star"},{"name":"TOI-3629-b","texture":"TOI-3629-b","m":0.000248118,"worldType":"sudarsky class three","atmosphere":"dodgerblue","discoveryFacility":"Transit","potentiallyHabitableWorld":false,"radius":722.7906976744187,"a":0.043,"e":0.05,"w":-110,"i":0,"o":0,"orbitalPeriod":3.936551,"temperature":690,"exoplanet":true,"bump":false,"color":"#33E81D","clouds":false,"customCameraPosition":{"x":2,"y":2,"z":0}}],"hallOfFame":false,"scenarioDescription":"\n  <ul class=\"exoplanets-navigation-menu\">\n  <li><button href=\"#system\">System</button>\n  <li><button href=\"#TOI-3629\">Star</button>\n  <li><button href=\"#TOI-3629-b\">b</button></li>\n  </ul>\n  <h1 id=\"system\">The TOI-3629 Exoplanetary System</h1>\n  <p>The TOI-3629 system contains 1 exoplanet. It is located 424.30 light years away from the solar system.</p>\n    <div class=\"celestial-object-wrapper\" id=\"TOI-3629\">\n  <section>\n  <h2>Star</h2>\n  <div class=\"size-comparison-wrapper\">\n  <div class=\"celestial-sphere\" style=\"width: 100px; height: 100px; background-color: rgb(255, 242.3979365143785, 230.54885609599933);\">\n    <label>Sun</label>\n  </div>\n  <div class=\"celestial-sphere\" style=\"width: 60px; height: 60px; background-color: rgb(255, 202.52973097550148, 159.94498066413968)\">\n<label>TOI-3629</label>\n</div>\n</div>\n  </section>\n  <table cellspacing=\"0\">\n  <tr>\n    <td>Mass</td>\n    <td>0.63 solar masses</td>\n  </tr>\n  <tr>\n    <td>Radius</td>\n    <td>0.6 solar radiae</td>\n  </tr>\n  <tr>\n    <td>Temperature</td>\n    <td>3870 kelvin</td>\n  </tr>\n  <tr>\n    <td>Stellar Metallicity</td>\n    <td>0.4 decimal exponent</td>\n  </tr>\n  <tr>\n    <td>Age</td>\n    <td>7 billion years</td>\n  </tr>\n</table>\n</div>\n     \n    <div class=\"celestial-object-wrapper\" id=\"TOI-3629-b\">\n      <section>\n        <h2>TOI-3629-b</h2>\n        <p>     At more than 50 Earth masses, TOI-3629 b is a gas giant, a planet whose mass is mostly made up of hydrogen and helium, like Jupiter and Saturn. </p>\n        <div class=\"size-comparison-wrapper\">\n          <div class=\"celestial-sphere\" style=\"width: 10px; height: 10px;\">\n            <label>Earth</label>\n          </div>\n          <div class=\"celestial-sphere\" style=\"width: 82.95px; height: 82.95px;\">\n            <label>TOI-3629-b</label>\n          </div>\n        </div>\n        <table cellspacing=\"0\">\n          <tr>\n            <td>Mass</td>\n            <td>82.635 Earth masses</td>\n          </tr>\n          <tr>\n            <td>Density</td>\n            <td>0.800 grams per cubic centimeter</td>\n          </tr>\n          <tr>\n            <td>Radius</td>\n            <td>8.295 Earth radiae</td>\n          </tr>\n          <tr>\n            <td>Semi-major Axis</td>\n            <td>0.043 AU</td>\n          </tr>\n          <tr>\n            <td>Eccentricity</td>\n            <td>0.05</td>\n          </tr>\n          <tr>\n            <td>Orbital Period</td>\n            <td>3.937 days</td>\n          </tr>\n          <tr>\n            <td>Discovery Method</td>\n            <td>Transit</td>\n          </tr>\n          <tr>\n            <td>Discovery Facility</td>\n            <td>Transiting Exoplanet Survey Satellite (TESS)</td>\n          </tr>\n          <tr>\n            <td>Discovery Telescope</td>\n            <td>0.1 m TESS Telescope</td>\n          </tr>\n          <tr>\n            <td>Discovery Instrument</td>\n            <td>TESS CCD Array</td>\n          </tr>\n          <tr>\n            <td>Discovery Date</td>\n            <td>2022-01</td>\n          </tr>\n          <tr>\n            <td>Reference</td>\n            <td><a refstr=CA_NTILDE_AS_ET_AL__2022 href=https://ui.adsabs.harvard.edu/abs/2022arXiv220109963C/abstract target=ref>Ca&ntilde;as et al. 2022</a></td>\n          </tr>\n        </table>\n      </section>\n    </div></a>\n  ","description":"3D visualisation and gravity simulation of the exoplanetary system TOI-3629, which contains 1 exoplanets and was discovered by the Transiting Exoplanet Survey Satellite (TESS).","name":"TOI-3629 - System With 1 Exoplanet ","cameraFocus":"Barycenter","fileName":"TOI-3629 - System With 1 Exoplanet "}