{
  "name": "WASP-81",
  "discoveryFacility": "Multiple Facilities",
  "description": "3D visualisation and gravity simulation of the exoplanet system WASP-81, which contains 1 planets and was discovered by Multiple Facilities.",
  "particlesFun": false,
  "type": "Exoplanets",
  "pl_pnum": 1,
  "g": 39.5,
  "dt": 0.00005,
  "distMax": 50,
  "distMin": -50,
  "rotatingReferenceFrame": "WASP-81",
  "cameraFocus": "Barycenter",
  "particles": { "max": 20000, "size": 10, "rings": [] },
  "massBeingModified": "Mars",
  "primary": "WASP-81",
  "maximumDistance": { "name": "Phobos to Mars * 100", "value": 0.00626747 },
  "distanceStep": { "name": "Phobos to Mars / 10", "value": 0.00000626747 },
  "scenarioWikiUrl": "http://exoplanet.eu/catalog/wasp-81_b/",
  "systemBarycenter": true,
  "barycenter": true,
  "barycenterMassOne": "WASP-81",
  "barycenterMassTwo": "WASP-81",
  "tol": 0.0001,
  "maxDt": 0.001,
  "minDt": 0.000001,
  "drawLineEvery": 6,
  "isLoaded": false,
  "playing": false,
  "integrator": "PEFRL",
  "customCameraToBodyDistanceFactor": false,
  "barycenterZ": 246204,
  "elapsedTime": 0,
  "useBarnesHut": false,
  "theta": 0.5,
  "collisions": true,
  "habitableZone": true,
  "referenceOrbits": false,
  "softeningConstant": 0,
  "logarithmicDepthBuffer": false,
  "scale": 2100000,
  "trails": true,
  "labels": true,
  "trajectoryRendevouz": {
    "x": 0,
    "y": 0,
    "z": 0,
    "p": { "x": 0, "y": 0, "z": 0, "t": 0 }
  },
  "velMax": 5,
  "velMin": -5,
  "velStep": 0.00000185765499287888,
  "isMassBeingAdded": false,
  "a": 0,
  "e": 0,
  "w": 0,
  "i": 0,
  "o": 0,
  "masses": [
    {
      "name": "WASP-81",
      "m": 1.08,
      "radius": 12502.32558139535,
      "temperature": 5870,
      "massType": "star"
    },
    {
      "name": "WASP-81-b",
      "texture": "WASP-81-b",
      "m": 0.0006956847,
      "discoveryFacility": "Multiple Facilities",
      "potentiallyHabitableWorld": false,
      "radius": 855.3156070207448,
      "a": 0.03908,
      "e": 0.066,
      "w": 294.3297874138769,
      "o": 0,
      "orbitalPeriod": 2.7164762,
      "temperature": 1623,
      "scenarioWikiUrl": "http://exoplanet.eu/catalog/wasp-81_b/",
      "exoplanet": true,
      "bump": false,
      "color": "#96A545",
      "clouds": false
    }
  ]
}
